[
  {
    "id": "xwing",
    "size": "small",
    "factions": [
      "rebel"
    ],
    "stats": {
      "attack": 3,
      "agility": 2,
      "hull": 3,
      "shield": 2
    },
    "actions": [
      "focus",
      "targetlock"
    ],
    "maneuvers": [
      [0, 0, 0, 0, 0, 0],
      [0, 2, 2, 2, 0, 0],
      [1, 1, 2, 1, 1, 0],
      [1, 1, 1, 1, 1, 0],
      [0, 0, 1, 0, 0, 3]
    ]
  },
  {
    "id": "ywing",
    "size": "small",
    "factions": [
      "rebel",
      "scum"
    ],
    "stats": {
      "attack": 2,
      "agility": 1,
      "hull": 5,
      "shield": 3
    },
    "actions": [
      "focus",
      "targetlock"
    ],
    "maneuvers": [
      [0, 0, 0, 0, 0, 0],
      [0, 1, 2, 1, 0, 0],
      [1, 1, 2, 1, 1, 0],
      [3, 1, 1, 1, 3, 0],
      [0, 0, 3, 0, 0, 3]
    ]
  },
  {
    "id": "yt1300",
    "size": "large",
    "factions": [
      "rebel"
    ],
    "stats": {
      "attack": 3,
      "agility": 1,
      "hull": 8,
      "shield": 5,
      "firingArc": "turret"
    },
    "actions": [
      "focus",
      "targetlock"
    ],
    "maneuvers": [
      [0, 0, 0, 0, 0, 0],
      [1, 2, 2, 2, 1, 0],
      [1, 1, 2, 1, 1, 0],
      [1, 1, 1, 1, 1, 3],
      [0, 0, 1, 0, 0, 3]
    ]
  },
  {
    "id": "awing",
    "size": "small",
    "factions": [
      "rebel"
    ],
    "stats": {
      "attack": 2,
      "agility": 3,
      "hull": 2,
      "shield": 2
    },
    "actions": [
      "focus",
      "targetlock",
      "boost",
      "evade"
    ],
    "maneuvers": [
      [0, 0, 0, 0, 0, 0],
      [1, 0, 0, 0, 1, 0],
      [2, 2, 2, 2, 2, 0],
      [1, 1, 2, 1, 1, 3],
      [0, 0, 2, 0, 0, 0],
      [0, 0, 2, 0, 0, 3]
    ]
  },
  {
    "id": "hwk290",
    "size": "small",
    "factions": [
      "rebel",
      "scum"
    ],
    "stats": {
      "attack": 1,
      "agility": 2,
      "hull": 4,
      "shield": 1
    },
    "actions": [
      "focus",
      "targetlock"
    ],
    "maneuvers": [
      [0, 0, 0, 0, 0, 0],
      [0, 2, 2, 2, 0, 0],
      [1, 1, 2, 1, 1, 0],
      [0, 3, 1, 3, 0, 0],
      [0, 0, 3, 0, 0, 0]
    ]
  },
  {
    "id": "bwing",
    "size": "small",
    "factions": [
      "rebel"
    ],
    "stats": {
      "attack": 3,
      "agility": 1,
      "hull": 3,
      "shield": 5
    },
    "actions": [
      "focus",
      "targetlock",
      "barrelroll"
    ],
    "maneuvers": [
      [0, 0, 0, 0, 0, 0],
      [3, 2, 2, 2, 3, 0],
      [1, 1, 2, 1, 1, 3],
      [0, 3, 1, 3, 0, 0],
      [0, 0, 3, 0, 0, 0]
    ]
  },
  {
    "id": "gr75mediumtransporter",
    "size": "huge",
    "epicPoints": 2,
    "factions": [
      "rebel"
    ],
    "stats": {
      "energy": 4,
      "agility": 0,
      "hull": 8,
      "shield": 4
    },
    "actions": [
      "recover",
      "reinforce",
      "coordinate",
      "jam"
    ],
    "maneuvers": [
      [0, 0, 0, 0, 0, 0],
      [0, 1, 1, 1, 0, 0],
      [0, 1, 1, 1, 0, 0],
      [0, 0, 1, 0, 0, 0],
      [0, 0, 1, 0, 0, 0]
    ]
  },
  {
    "id": "z95headhunter",
    "size": "small",
    "factions": [
      "rebel",
      "scum"
    ],
    "stats": {
      "attack": 2,
      "agility": 2,
      "hull": 2,
      "shield": 2
    },
    "actions": [
      "focus",
      "targetlock"
    ],
    "maneuvers": [
      [0, 0, 0, 0, 0, 0],
      [0, 1, 2, 1, 0, 0],
      [1, 2, 2, 2, 1, 0],
      [1, 1, 1, 1, 1, 3],
      [0, 0, 1, 0, 0, 0]
    ]
  },
  {
    "id": "ewing",
    "size": "small",
    "factions": [
      "rebel"
    ],
    "stats": {
      "attack": 3,
      "agility": 3,
      "hull": 2,
      "shield": 3
    },
    "actions": [
      "focus",
      "targetlock",
      "barrelroll",
      "evade"
    ],
    "maneuvers": [
      [0, 0, 0, 0, 0, 0],
      [0, 1, 2, 1, 0, 0],
      [1, 2, 2, 2, 1, 0],
      [1, 1, 2, 1, 1, 3],
      [0, 0, 1, 0, 0, 3],
      [0, 0, 1, 0, 0, 0]
    ]
  },
  {
    "id": "cr90corvettefore",
    "canonicalId": "cr90corvette",
    "size": "huge",
    "epicPoints": 1.5,
    "factions": [
      "rebel"
    ],
    "stats": {
      "attack": 4,
      "agility": 0,
      "hull": 8,
      "shield": 5,
      "firingArc": "turret"
    },
    "actions": [
      "coordinate",
      "targetlock"
    ],
    "maneuvers": [
      [0, 0, 0, 0, 0, 0],
      [0, 1, 0, 1, 0, 0],
      [0, 1, 1, 1, 0, 0],
      [0, 0, 1, 0, 0, 0],
      [0, 0, 1, 0, 0, 0]
    ],
    "multisection": [
      "cr90corvetteaft"
    ]
  },
  {
    "id": "cr90corvetteaft",
    "canonicalId": "cr90corvette",
    "size": "huge",
    "epicPoints": 1.5,
    "factions": [
      "rebel"
    ],
    "stats": {
      "energy": 5,
      "agility": 0,
      "hull": 8,
      "shield": 3
    },
    "actions": [
      "reinforce",
      "recover"
    ],
    "maneuvers": [
      [0, 0, 0, 0, 0, 0],
      [0, 1, 0, 1, 0, 0],
      [0, 1, 1, 1, 0, 0],
      [0, 0, 1, 0, 0, 0],
      [0, 0, 1, 0, 0, 0]
    ],
    "multisection": [
      "cr90corvettefore"
    ]
  },
  {
    "id": "yt2400",
    "size": "large",
    "factions": [
      "rebel"
    ],
    "stats": {
      "attack": 2,
      "agility": 2,
      "hull": 5,
      "shield": 5,
      "firingArc": "turret"
    },
    "actions": [
      "focus",
      "targetlock",
      "barrelroll"
    ],
    "maneuvers": [
      [0, 0, 0, 0, 0, 0],
      [1, 2, 2, 2, 1, 0],
      [1, 1, 2, 1, 1, 0],
      [1, 1, 1, 1, 1, 0],
      [0, 0, 1, 0, 0, 3]
    ]
  },
  {
    "id": "kwing",
    "size": "small",
    "factions": [
      "rebel"
    ],
    "stats": {
      "attack": 2,
      "agility": 1,
      "hull": 5,
      "shield": 4
    },
    "actions": [
      "focus",
      "targetlock",
      "slam"
    ],
    "maneuvers": [
      [0, 0, 0, 0, 0, 0],
      [0, 2, 2, 2, 0, 0],
      [1, 1, 2, 1, 1, 0],
      [0, 1, 1, 1, 0, 0]
    ]
  },
  {
    "id": "t70xwing",
    "size": "small",
    "factions": [
      "rebel"
    ],
    "stats": {
      "attack": 3,
      "agility": 2,
      "hull": 3,
      "shield": 3
    },
    "actions": [
      "focus",
      "targetlock",
      "boost"
    ],
    "maneuvers": [
      [0, 0, 0, 0, 0, 0, 0, 0, 0, 0],
      [0, 2, 2, 2, 0, 0, 0, 0, 0, 0],
      [1, 1, 2, 1, 1, 0, 0, 0, 0, 0],
      [1, 1, 2, 1, 1, 0, 0, 0, 3, 3],
      [0, 0, 1, 0, 0, 3, 0, 0, 0, 0]
    ]
  },
  {
    "id": "vcx100",
    "size": "large",
    "factions": [
      "rebel"
    ],
    "stats": {
      "attack": 4,
      "agility": 0,
      "hull": 10,
      "shield": 6
    },
    "actions": [
      "focus",
      "targetlock",
      "evade"
    ],
    "maneuvers": [
      [0, 0, 0, 0, 0, 0],
      [3, 1, 2, 1, 3, 0],
      [1, 2, 2, 2, 1, 0],
      [3, 1, 1, 1, 3, 0],
      [0, 0, 1, 0, 0, 0],
      [0, 0, 0, 0, 0, 3]
    ]
  },
  {
    "id": "attackshuttle",
    "size": "small",
    "factions": [
      "rebel"
    ],
    "stats": {
      "attack": 3,
      "agility": 2,
      "hull": 2,
      "shield": 2
    },
    "actions": [
      "focus",
      "barrelroll",
      "evade"
    ],
    "maneuvers": [
      [0, 0, 0, 0, 0, 0],
      [3, 2, 2, 2, 3, 0],
      [1, 1, 2, 1, 1, 0],
      [3, 1, 1, 1, 3, 0],
      [0, 0, 1, 0, 0, 3]
    ]
  },
  {
    "id": "arc170",
    "size": "small",
    "factions": [
      "rebel"
    ],
    "stats": {
      "attack": 2,
      "agility": 1,
      "hull": 6,
      "shield": 3
    },
    "actions": [
      "focus",
      "targetlock"
    ],
    "maneuvers": [
      [0, 0, 0, 0, 0, 0],
      [0, 2, 2, 2, 0, 0],
      [1, 2, 2, 2, 1, 0],
      [3, 1, 1, 1, 3, 0],
      [0, 0, 3, 0, 0, 3]
    ]
  },
  {
    "id": "uwing",
    "size": "large",
    "factions": [
      "rebel"
    ],
    "stats": {
      "attack": 3,
      "agility": 1,
      "hull": 4,
      "shield": 4
    },
    "actions": [
      "focus",
      "targetlock"
    ],
    "maneuvers": [
      [0, 0, 3, 0, 0, 0],
      [0, 2, 2, 2, 0, 0],
      [1, 2, 2, 2, 1, 0],
      [0, 1, 1, 1, 0, 0],
      [0, 0, 1, 0, 0, 0]
    ]
  },
  {
    "id": "auzituckgunship",
    "size": "small",
    "factions": [
      "rebel"
    ],
    "stats": {
      "attack": 3,
      "agility": 1,
      "hull": 6,
      "shield": 3,
      "firingarc": "degree180"
    },
    "actions": [
      "focus",
      "reinforce"
    ],
    "maneuvers": [
      [0, 0, 0, 0, 0, 0],
      [0, 2, 2, 2, 0, 0],
      [1, 1, 2, 1, 1, 0],
      [1, 1, 2, 1, 1, 0],
      [0, 0, 1, 0, 0, 0],
      [0, 0, 3, 0, 0, 0]
    ]
  },
  {
    "id": "bsf17bomber",
    "size": "large",
    "factions": [
      "rebel"
    ],
    "stats": {
      "attack": 2,
      "agility": 1,
      "hull": 9,
      "shield": 3,
      "firingArc": "turret"
    },
    "actions": [
      "focus",
      "targetlock"
    ],
    "maneuvers": [
      [0, 0, 3, 0, 0, 0],
      [3, 2, 2, 2, 3, 0],
      [1, 1, 2, 1, 1, 0],
      [0, 1, 1, 1, 0, 0]
    ]
  },
  {
    "id": "sheathipedeclassshuttle",
    "size": "small",
    "factions": [
      "rebel"
    ],
    "stats": {
      "attack": 2,
      "agility": 2,
      "hull": 4,
      "shield": 1,
      "firingArc": "frontback"
    },
    "actions": [
      "focus",
      "targetlock",
      "coordinate"
    ],
    "maneuvers": [
      [0, 0, 0, 0, 0, 0],
      [0, 1, 2, 1, 0, 0],
      [1, 2, 2, 2, 1, 0],
      [3, 1, 2, 1, 3, 3],
      [0, 0, 3, 0, 0, 0]
    ]
  },


  {
    "id": "tiefighter",
    "size": "small",
    "factions": [
      "imperial",
      "rebel"
    ],
    "stats": {
      "attack": 2,
      "agility": 3,
      "hull": 3,
      "shield": 0
    },
    "actions": [
      "focus",
      "barrelroll",
      "evade"
    ],
    "maneuvers": [
      [0, 0, 0, 0, 0, 0],
      [1, 0, 0, 0, 1, 0],
      [1, 2, 2, 2, 1, 0],
      [1, 1, 2, 1, 1, 3],
      [0, 0, 1, 0, 0, 3],
      [0, 0, 1, 0, 0, 0]
    ]
  },
  {
    "id": "tieadvanced",
    "size": "small",
    "factions": [
      "imperial"
    ],
    "stats": {
      "attack": 2,
      "agility": 3,
      "hull": 3,
      "shield": 2
    },
    "actions": [
      "focus",
      "targetlock",
      "barrelroll",
      "evade"
    ],
    "maneuvers": [
      [0, 0, 0, 0, 0, 0],
      [0, 2, 0, 2, 0, 0],
      [1, 1, 2, 1, 1, 0],
      [1, 1, 2, 1, 1, 0],
      [0, 0, 1, 0, 0, 3],
      [0, 0, 1, 0, 0, 0]
    ]
  },
  {
    "id": "firespray31",
    "size": "large",
    "factions": [
      "imperial",
      "scum"
    ],
    "stats": {
      "attack": 3,
      "agility": 2,
      "hull": 6,
      "shields": 4,
      "firingArc": "frontback"
    },
    "actions": [
      "focus",
      "targetlock",
      "evade"
    ],
    "maneuvers": [
      [0, 0, 0, 0, 0, 0],
      [0, 2, 2, 2, 0, 0],
      [1, 1, 2, 1, 1, 0],
      [1, 1, 1, 1, 1, 3],
      [0, 0, 1, 0, 0, 3]
    ]
  },
  {
    "id": "tieinterceptor",
    "size": "small",
    "factions": [
      "imperial"
    ],
    "stats": {
      "attack": 3,
      "agility": 3,
      "hull": 3,
      "shield": 0
    },
    "actions": [
      "focus",
      "barrelroll",
      "boost",
      "evade"
    ],
    "maneuvers": [
      [0, 0, 0, 0, 0, 0],
      [1, 0, 0, 0, 1, 0],
      [2, 2, 2, 2, 2, 0],
      [1, 1, 2, 1, 1, 3],
      [0, 0, 2, 0, 0, 0],
      [0, 0, 2, 0, 0, 3]
    ]
  },
  {
    "id": "lambdaclassshuttle",
    "size": "large",
    "factions": [
      "imperial"
    ],
    "stats": {
      "attack": 3,
      "agility": 1,
      "hull": 5,
      "shield": 5
    },
    "actions": [
      "focus",
      "targetlock"
    ],
    "maneuvers": [
      [0, 0, 3, 0, 0, 0],
      [0, 2, 2, 2, 0, 0],
      [3, 1, 2, 1, 3, 0],
      [0, 3, 1, 3, 0, 0]
    ]
  },
  {
    "id": "tiebomber",
    "size": "small",
    "factions": [
      "imperial"
    ],
    "stats": {
      "attack": 2,
      "agility": 2,
      "hull": 6,
      "shield": 0
    },
    "actions": [
      "focus",
      "targetlock",
      "barrelroll"
    ],
    "maneuvers": [
      [0, 0, 0, 0, 0, 0],
      [0, 1, 2, 1, 0, 0],
      [3, 2, 2, 2, 3, 0],
      [1, 1, 2, 1, 1, 0],
      [0, 0, 1, 0, 0, 0],
      [0, 0, 0, 0, 0, 3]
    ]
  },
  {
    "id": "tiedefender",
    "size": "small",
    "factions": [
      "imperial"
    ],
    "stats": {
      "attack": 3,
      "agility": 3,
      "hull": 3,
      "shield": 3
    },
    "actions": [
      "focus",
      "targetlock",
      "barrelroll"
    ],
    "maneuvers": [
      [0, 0, 0, 0, 0, 0],
      [3, 1, 0, 1, 3, 0],
      [3, 1, 2, 1, 3, 0],
      [1, 1, 2, 1, 1, 0],
      [0, 0, 2, 0, 0, 1],
      [0, 0, 2, 0, 0, 0]
    ]
  },
  {
    "id": "tiephantom",
    "size": "small",
    "factions": [
      "imperial"
    ],
    "stats": {
      "attack": 4,
      "agility": 2,
      "hull": 2,
      "shield": 2
    },
    "actions": [
      "focus",
      "barrelroll",
      "evade",
      "cloak"
    ],
    "maneuvers": [
      [0, 0, 0, 0, 0, 0],
      [1, 0, 0, 0, 1, 0],
      [1, 2, 2, 2, 1, 0],
      [1, 1, 2, 1, 1, 3],
      [0, 0, 1, 0, 0, 3]
    ]
  },
  {
    "id": "vt49decimator",
    "size": "large",
    "factions": [
      "imperial"
    ],
    "stats": {
      "attack": 3,
      "agility": 0,
      "hull": 12,
      "shield": 4,
      "firingArc": "turret"
    },
    "actions": [
      "focus",
      "targetlock"
    ],
    "maneuvers": [
      [0, 0, 0, 0, 0, 0],
      [0, 1, 1, 1, 0, 0],
      [1, 2, 2, 2, 1, 0],
      [1, 1, 2, 1, 1, 0],
      [0, 0, 1, 0, 0, 0]
    ]
  },
  {
    "id": "raiderclasscorvettefore",
    "canonicalId": "raiderclasscorvette",
    "size": "huge",
    "epicPoints": 1.5,
    "factions": [
      "imperial"
    ],
    "stats": {
      "attack": 4,
      "agility": 0,
      "hull": 8,
      "shield": 6,
      "range": "2-4"
    },
    "actions": [
      "reinforce",
      "recover"
    ],
    "maneuvers": [
      [0, 0, 0, 0, 0, 0],
      [0, 1, 1, 1, 0, 0],
      [0, 1, 1, 1, 0, 0],
      [0, 0, 1, 0, 0, 0],
      [0, 0, 1, 0, 0, 0]
    ],
    "multisection": [
      "raiderclasscorvetteaft"
    ]
  },
  {
    "id": "raiderclasscorvetteaft",
    "canonicalId": "raiderclasscorvette",
    "size": "huge",
    "epicPoints": 1.5,
    "factions": [
      "imperial"
    ],
    "stats": {
      "energy": 6,
      "agility": 0,
      "hull": 8,
      "shield": 4
    },
    "actions": [
      "coordinate",
      "targetlock"
    ],
    "maneuvers": [
      [0, 0, 0, 0, 0, 0],
      [0, 1, 1, 1, 0, 0],
      [0, 1, 1, 1, 0, 0],
      [0, 0, 1, 0, 0, 0],
      [0, 0, 1, 0, 0, 0]
    ],
    "multisection": [
      "raiderclasscorvettefore"
    ]
  },
  {
    "id": "tiepunisher",
    "size": "small",
    "factions": [
      "imperial"
    ],
    "stats": {
      "attack": 2,
      "agility": 1,
      "hull": 6,
      "shield": 3
    },
    "actions": [
      "focus",
      "targetlock",
      "boost"
    ],
    "maneuvers": [
      [0, 0, 0, 0, 0, 0],
      [0, 2, 2, 2, 0, 0],
      [3, 1, 2, 1, 3, 0],
      [1, 1, 1, 1, 1, 0],
      [0, 0, 0, 0, 0, 3]
    ]
  },
  {
    "id": "gozanticlasscruiser",
    "size": "huge",
    "epicPoints": 2,
    "factions": [
      "imperial"
    ],
    "stats": {
      "energy": 4,
      "agility": 0,
      "hull": 9,
      "shield": 5
    },
    "actions": [
      "recover",
      "reinforce",
      "coordinate",
      "targetlock"
    ],
    "maneuvers": [
      [0, 0, 0, 0, 0, 0],
      [0, 1, 1, 1, 0, 0],
      [0, 1, 1, 1, 0, 0],
      [0, 0, 1, 0, 0, 0],
      [0, 0, 1, 0, 0, 0]
    ]
  },
  {
    "id": "tiefofighter",
    "size": "small",
    "factions": [
      "imperial"
    ],
    "stats": {
      "attack": 2,
      "agility": 3,
      "hull": 3,
      "shield": 1
    },
    "actions": [
      "focus",
      "targetlock",
      "barrelroll",
      "evade"
    ],
    "maneuvers": [
      [0, 0, 0, 0, 0, 0, 0, 0],
      [1, 0, 0, 0, 1, 0, 0, 0],
      [2, 2, 2, 2, 2, 0, 3, 3],
      [1, 1, 2, 1, 1, 0, 0, 0],
      [0, 0, 1, 0, 0, 3, 0, 0],
      [0, 0, 1, 0, 0, 0, 0, 0]
    ]
  },
  {
    "id": "tieadvprototype",
    "size": "small",
    "factions": [
      "imperial"
    ],
    "stats": {
      "attack": 2,
      "agility": 3,
      "hull": 2,
      "shield": 2
    },
    "actions": [
      "focus",
      "targetlock",
      "barrelroll",
      "boost"
    ],
    "maneuvers": [
      [0, 0, 0, 0, 0, 0],
      [2, 2, 0, 2, 2, 0],
      [1, 1, 2, 1, 1, 0],
      [1, 1, 2, 1, 1, 0],
      [0, 0, 2, 0, 0, 3],
      [0, 0, 1, 0, 0, 0]
    ]
  },
  {
    "id": "tiesffighter",
    "size": "small",
    "factions": [
      "imperial"
    ],
    "stats": {
      "attack": 2,
      "agility": 2,
      "hull": 3,
      "shield": 3
    },
    "actions": [
      "focus",
      "targetlock",
      "barrelroll"
    ],
    "maneuvers": [
      [0, 0, 0, 0, 0, 0, 0, 0],
      [3, 2, 2, 2, 3, 0, 0, 0],
      [1, 1, 2, 1, 1, 0, 0, 0],
      [3, 1, 2, 1, 3, 0, 3, 3],
      [0, 0, 1, 0, 0, 0, 0, 0]
    ]
  },
  {
    "id": "upsilonclassshuttle",
    "size": "large",
    "factions": [
      "imperial"
    ],
    "stats": {
      "attack": 4,
      "agility": 1,
      "hull": 6,
      "shield": 6
    },
    "actions": [
      "focus",
      "targetlock",
      "coordinate"
    ],
    "maneuvers": [
      [0, 0, 3, 0, 0, 0],
      [3, 1, 2, 1, 3, 0],
      [1, 2, 2, 2, 1, 0],
      [3, 1, 1, 1, 3, 0]
    ]
  },
  {
    "id": "tiestriker",
    "size": "small",
    "factions": [
      "imperial"
    ],
    "stats": {
      "attack": 3,
      "agility": 2,
      "hull": 4,
      "shield": 0
    },
    "actions": [
      "focus",
      "barrelroll",
      "evade"
    ],
    "maneuvers": [
      [0, 0, 0, 0, 0, 0, 0, 0],
      [1, 2, 2, 2, 1, 0, 0, 0],
      [1, 1, 2, 1, 1, 3, 3, 3],
      [0, 1, 2, 1, 0, 0, 0, 0]
    ]
  },
  {
    "id": "tieaggressor",
    "size": "small",
    "factions": [
      "imperial"
    ],
    "stats": {
      "attack": 2,
      "agility": 2,
      "hull": 4,
      "shield": 1
    },
    "actions": [
      "focus",
      "targetlock",
      "barrelroll"
    ],
    "maneuvers": [
      [0, 0, 0, 0, 0, 0],
      [0, 1, 2, 1, 0, 0],
      [1, 2, 2, 2, 1, 0],
      [1, 1, 2, 1, 1, 0],
      [0, 0, 1, 0, 0, 3]
    ]
  },
  {
    "id": "tiesilencer",
    "size": "small",
    "factions": [
      "imperial"
    ],
    "stats": {
      "attack": 3,
      "agility": 3,
      "hull": 4,
      "shield": 2
    },
    "actions": [
      "focus",
      "targetlock",
      "barrelroll",
      "boost"
    ],
    "maneuvers": [
      [0, 0, 0, 0, 0, 0, 0, 0, 0, 0],
      [1, 0, 0, 0, 1, 0, 0, 0, 0, 0],
      [2, 2, 2, 2, 2, 0, 0, 0, 0, 0],
      [1, 2, 2, 2, 1, 0, 0, 0, 3, 3],
      [0, 0, 2, 0, 0, 3, 0, 0, 0, 0],
      [0, 0, 2, 0, 0, 0, 0, 0, 0, 0]
    ]
  },
  {
    "id": "alphaclassstarwing",
    "size": "small",
    "factions": [
      "imperial"
    ],
    "stats": {
      "attack": 2,
      "agility": 2,
      "hull": 4,
      "shield": 3
    },
    "actions": [
      "focus",
      "targetlock",
      "slam",
      "reload"
    ],
    "maneuvers": [
      [0, 0, 0, 0, 0, 0],
      [0, 1, 1, 1, 0, 0],
      [1, 2, 2, 2, 1, 0],
      [1, 1, 1, 1, 1, 0],
      [0, 0, 3, 0, 0, 0]
    ]
  },


  {
    "id": "starviper",
    "size": "small",
    "factions": [
      "scum"
    ],
    "stats": {
      "attack": 3,
      "agility": 3,
      "hull": 4,
      "shield": 1
    },
    "actions": [
      "focus",
      "targetlock",
      "barrelroll",
      "boost"
    ],
    "maneuvers": [
      [0, 0, 0, 0, 0, 0, 0, 0],
      [1, 2, 2, 2, 1, 0, 0, 0],
      [1, 1, 2, 1, 1, 0, 0, 0],
      [0, 1, 2, 1, 0, 0, 3, 3],
      [0, 0, 1, 0, 0, 0, 0, 0]
    ]
  },
  {
    "id": "m3ainterceptor",
    "size": "small",
    "factions": [
      "scum"
    ],
    "stats": {
      "attack": 2,
      "agility": 3,
      "hull": 2,
      "shield": 1
    },
    "actions": [
      "focus",
      "targetlock",
      "barrelroll",
      "evade"
    ],
    "maneuvers": [
      [0, 0, 0, 0, 0, 0],
      [1, 2, 0, 2, 1, 0],
      [1, 2, 2, 2, 1, 0],
      [0, 1, 2, 1, 0, 3],
      [0, 0, 1, 0, 0, 0],
      [0, 0, 0, 0, 0, 3]
    ]
  },
  {
    "id": "aggressor",
    "size": "large",
    "factions": [
      "scum"
    ],
    "stats": {
      "attack": 3,
      "agility": 3,
      "hull": 4,
      "shield": 4
    },
    "actions": [
      "focus",
      "targetlock",
      "boost",
      "evade"
    ],
    "maneuvers": [
      [0, 0, 0, 0, 0, 0, 0, 0],
      [1, 2, 2, 2, 1, 0, 0, 0],
      [1, 2, 2, 2, 1, 0, 0, 0],
      [0, 2, 2, 2, 0, 0, 3, 3],
      [0, 0, 0, 0, 0, 3, 0, 0]
    ]
  },
  {
    "id": "yv666",
    "size": "large",
    "factions": [
      "scum"
    ],
    "stats": {
      "attack": 3,
      "agility": 1,
      "hull": 6,
      "shield": 6
    },
    "actions": [
      "focus",
      "targetlock"
    ],
    "maneuvers": [
      [0, 0, 3, 0, 0, 0],
      [0, 2, 2, 2, 0, 0],
      [3, 1, 2, 1, 3, 0],
      [1, 1, 2, 1, 1, 0],
      [0, 0, 1, 0, 0, 0]
    ]
  },
  {
    "id": "kihraxzfighter",
    "size": "small",
    "factions": [
      "scum"
    ],
    "stats": {
      "attack": 3,
      "agility": 2,
      "hull": 4,
      "shield": 1
    },
    "actions": [
      "focus",
      "targetlock"
    ],
    "maneuvers": [
      [0, 0, 0, 0, 0, 0],
      [1, 2, 0, 2, 1, 0],
      [1, 2, 2, 2, 1, 0],
      [0, 1, 1, 1, 0, 0],
      [0, 0, 1, 0, 0, 3],
      [0, 0, 0, 0, 0, 3]
    ]
  },
  {
    "id": "g1astarfighter",
    "size": "small",
    "factions": [
      "scum"
    ],
    "stats": {
      "attack": 3,
      "agility": 1,
      "hull": 4,
      "shield": 4
    },
    "actions": [
      "focus",
      "targetlock",
      "evade"
    ],
    "maneuvers": [
      [0, 0, 0, 0, 0, 0],
      [3, 2, 2, 2, 3, 0],
      [1, 1, 2, 1, 1, 0],
      [0, 3, 2, 3, 0, 3],
      [0, 0, 1, 0, 0, 3]
    ]
  },
  {
    "id": "jumpmaster5000",
    "size": "large",
    "factions": [
      "scum"
    ],
    "stats": {
      "attack": 2,
      "agility": 2,
      "hull": 5,
      "shield": 4,
      "firingArc": "turret"
    },
    "actions": [
      "focus",
      "targetlock",
      "barrelroll"
    ],
    "maneuvers": [
      [0, 0, 0, 0, 0, 0, 0, 0],
      [2, 2, 2, 1, 1, 0, 0, 0],
      [2, 2, 2, 1, 1, 0, 1, 3],
      [0, 1, 1, 1, 0, 0, 0, 0],
      [0, 0, 1, 0, 0, 3, 0, 0]
    ]
  },
  {
    "id": "protectoratestarfighter",
    "size": "small",
    "factions": [
      "scum"
    ],
    "stats": {
      "attack": 3,
      "agility": 3,
      "hull": 4,
      "shield": 0
    },
    "actions": [
      "focus",
      "targetlock",
      "barrelroll",
      "boost"
    ],
    "maneuvers": [
      [0, 0, 0, 0, 0, 0, 0, 0, 0, 0],
      [1, 0, 0, 0, 1, 0, 0, 0, 0, 0],
      [2, 2, 2, 2, 2, 0, 0, 0, 3, 3],
      [1, 1, 2, 1, 1, 0, 0, 0, 0, 0],
      [0, 0, 1, 0, 0, 3, 0, 0, 0, 0],
      [0, 0, 1, 0, 0, 0, 0, 0, 0, 0]
    ]
  },
  {
    "id": "lancerclasspursuitcraft",
    "size": "large",
    "factions": [
      "scum"
    ],
    "stats": {
      "attack": 3,
      "agility": 2,
      "hull": 7,
      "shield": 3
    },
    "actions": [
      "focus",
      "targetlock",
      "evade",
      "rotatearc"
    ],
    "maneuvers": [
      [0, 0, 0, 0, 0, 0],
      [0, 1, 1, 1, 0, 0],
      [1, 1, 2, 1, 1, 0],
      [2, 2, 2, 2, 2, 0],
      [0, 0, 2, 0, 0, 0],
      [0, 0, 1, 0, 0, 3]
    ]
  },
  {
    "id": "croccruiser",
    "size": "huge",
    "epicPoints": 0,
    "factions": [
      "scum"
    ],
    "stats": {
      "energy": 4,
      "agility": 0,
      "hull": 10,
      "shield": 4
    },
    "actions": [
      "recover",
      "reinforce",
      "targetlock",
      "jam"
    ],
    "maneuvers": [
      [0, 0, 0, 0, 0, 0],
      [0, 1, 1, 1, 0, 0],
      [0, 1, 1, 1, 0, 0],
      [0, 0, 1, 0, 0, 0],
      [0, 0, 1, 0, 0, 0]
    ]
  },
  {
    "id": "quadjumper",
    "size": "small",
    "factions": [
      "scum"
    ],
    "stats": {
      "attack": 2,
      "agility": 2,
      "hull": 5,
      "shield": 0
    },
    "actions": [
      "focus",
      "barrelroll"
    ],
    "maneuvers": [
      [0, 0, 0, 0, 0, 0, 0, 0, 0, 0, 0, 0, 0],
      [1, 0, 1, 0, 1, 0, 0, 0, 0, 0, 3, 3, 3],
      [1, 2, 2, 2, 1, 0, 3, 3, 0, 0, 0, 0, 0],
      [0, 1, 2, 1, 0, 0, 0, 0, 0, 0, 0, 0, 0]
    ]
  },
  {
    "id": "scurrgh6bomber",
    "size": "small",
    "factions": [
      "scum",
      "rebel"
    ],
    "stats": {
      "attack": 3,
      "agility": 1,
      "hull": 5,
      "shield": 5
    },
    "actions": [
      "focus",
      "targetlock",
      "barrelroll"
    ],
    "maneuvers": [
      [0, 0, 0, 0, 0, 0, 0, 0, 0, 0],
      [0, 1, 2, 1, 0, 0, 0, 0, 0, 0],
      [1, 2, 2, 2, 1, 0, 0, 0, 0, 0],
      [3, 1, 2, 1, 3, 0, 0, 0, 3, 3],
      [0, 0, 1, 0, 0, 0, 0, 0, 0, 0],
      [0, 0, 3, 0, 0, 0, 0, 0, 0, 0]
    ]
  },
  {
    "id": "m12lkimogilafighter",
    "size": "small",
    "factions": [
      "scum"
    ],
    "stats": {
      "attack": 3,
      "agility": 1,
      "hull": 6,
      "shield": 2,
      "firingArc": "bullseye"
    },
    "actions": [
      "focus",
      "targetlock",
      "barrelroll",
      "reload"
    ],
    "maneuvers": [
      [0, 0, 0, 0, 0, 0],
      [3, 1, 2, 1, 3, 0],
      [3, 2, 2, 2, 3, 0],
      [1, 1, 2, 1, 1, 0],
      [0, 0, 0, 0, 0, 3]
    ]
  }
]
